{

  "sites": [
    {
      "key":"drpy_js_豆瓣",
      "name":"搜索 | 豆瓣(JS)",
      "type":3,
      "api":"https://agit.ai/cqpzq/gao/raw/branch/master/lib/drpy2.min.js",
      "ext":"https://agit.ai/cqpzq/gao/raw/branch/master/js/drpy.js"
    },
{"key": "csp_XYQHiker_土狗搜索","name":"土狗搜索(XYQH)","type":3,"api":"csp_XYQHiker","searchable":1,"quickSearch":1,"filterable":1,"ext":"https://download.kstore.space/download/4127/js/土狗搜索.json ","jar":"https://download.kstore.space/download/4127/Xiang.txt;md5; ffba26ea3e1400eaa63a9778a1d9524f"},

{"key": "csp_XYQHiker_DOVX搜索","name":"DOVX搜索","type":3,"api":"csp_XYQHiker","playerType":1,"searchable":1,"quickSearch":1,"filterable":1,"ext":"https://download.kstore.space/download/4127/js/DOVX搜索.json","jar":"https://download.kstore.space/download/4127/Xiang.txt;md5; ffba26ea3e1400eaa63a9778a1d9524f"},
        {"key": "csp_XYQHiker_盘搜索","name":"盘搜索","type":3,"api":"csp_XYQHiker","playerType":1,"searchable":1,"quickSearch":1,"filterable":1,"ext":"https://download.kstore.space/download/4127/js/盘搜索.json","jar":"https://download.kstore.space/download/4127/Xiang.txt;md5; ffba26ea3e1400eaa63a9778a1d9524f"},

{
            "key": "csp_Gitcafe",
            "name": "纸条搜索",
            "type": 3,
            "api": "csp_Gitcafe",
            "searchable": 1,
            "quickSearch": 1,
            "filterable": 1,
            "ext": "3317b053986748d9896f629eeaf498ae",
            "jar": "https://download.kstore.space/download/4127/Xiang.txt;md5; ffba26ea3e1400eaa63a9778a1d9524f"
        },
        {
            "key": "csp_Zhaozy",
            "name": "找资源",
            "type": 3,
            "api": "csp_Zhaozy",
            "searchable": 1,
            "quickSearch": 1,
            "filterable": 0,
            "ext": "https://agit.ai/809662687/dsb/raw/branch/master/TVBox/jar/alitoken.txt",
            "jar": "https://download.kstore.space/download/4127/Xiang.txt;md5; ffba26ea3e1400eaa63a9778a1d9524f"
        },
        {
            "key": "csp_AliPS",
            "name": "盘搜",
            "type": 3,
            "api": "csp_AliPS",
            "searchable": 1,
            "quickSearch": 1,
            "filterable": 0,
            "ext": "https://agit.ai/809662687/dsb/raw/branch/master/TVBox/jar/alitoken.txt",
            "jar": "https://download.kstore.space/download/4127/Xiang.txt;md5; ffba26ea3e1400eaa63a9778a1d9524f"
        },
        {
            "key": "csp_Yisou",
            "name": "易搜",
            "type": 3,
            "api": "csp_Yisou",
            "searchable": 1,
            "quickSearch": 1,
            "filterable": 0,
            "ext": "https://agit.ai/809662687/dsb/raw/branch/master/TVBox/jar/alitoken.txt",
            "jar": "https://download.kstore.space/download/4127/Xiang.txt;md5; ffba26ea3e1400eaa63a9778a1d9524f"
        },
        {
            "key": "csp_Upyunso",
            "name": "云搜",
            "type": 3,
            "api": "csp_Upyunso",
            "searchable": 1,
            "quickSearch": 1,
            "filterable": 0,
            "ext": "https://agit.ai/809662687/dsb/raw/branch/master/TVBox/jar/alitoken.txt",
            "jar": "https://download.kstore.space/download/4127/Xiang.txt;md5; ffba26ea3e1400eaa63a9778a1d9524f"
        }




]
}
